README.md
setup.py
ppyan/__init__.py
ppyan/authkey/__init__.py
ppyan/autoscrollbar/__init__.py
ppyan/autoscrollbar/autoscrbar.py
ppyan/caculate/__init__.py
ppyan/caculate/area.py
ppyan/caculate/cacul_cavas.py
ppyan/caculate/coord_point.py
ppyan/caculate/ratio.py
ppyan/cavas_dim/__init__.py
ppyan/cavas_dim/cavas_dim.py
ppyan/cavas_drawing/__init__.py
ppyan/cavas_drawing/buttondr.py
ppyan/cavas_drawing/draw.py
ppyan/cavas_write/__init__.py
ppyan/cavas_write/writetext.py
ppyan/cavaszm/__init__.py
ppyan/cavaszm/cavaszm.py
ppyan/check/Hstr_StrRetrFile_1.py
ppyan/check/__init__.py
ppyan/check/list.py
ppyan/checklb/__init__.py
ppyan/checklb/checkb.py
ppyan/crypt/__init__.py
ppyan/csv/__init__.py
ppyan/csv/rcsv.py
ppyan/csv/tocsv.py
ppyan/csv/todict.py
ppyan/csv/tolist.py
ppyan/ctn/__init__.py
ppyan/data/__init__.py
ppyan/data/filename.py
ppyan/data/hdata.py
ppyan/dict/__init__.py
ppyan/dict/createdict.py
ppyan/dict/csv.py
ppyan/error/__init__.py
ppyan/error/cerror.py
ppyan/excel/Fill_formula.py
ppyan/excel/__init__.py
ppyan/excel/convertexelltocsv.py
ppyan/excel/copy_move_paste.py
ppyan/excel/copyexcel.py
ppyan/excel/copypasteexell.py
ppyan/excel/crelistadict.py
ppyan/excel/del_row.py
ppyan/excel/delete.py
ppyan/excel/fexcell.py
ppyan/excel/fformulaexcel.py
ppyan/excel/fomulas.py
ppyan/excel/hdata.py
ppyan/excel/hexcel.py
ppyan/excel/hrow.py
ppyan/excel/lexcel.py
ppyan/excel/list.py
ppyan/excel/path.py
ppyan/excel/toexcel.py
ppyan/excel/write.py
ppyan/excel/exception/__init__.py
ppyan/excel/openpyxl/__init__.py
ppyan/excel/rows/__init__.py
ppyan/folder/__init__.py
ppyan/folder/list.py
ppyan/gdrive/__init__.py
ppyan/gdrive/sheet.py
ppyan/ggdrive/__init__.py
ppyan/ggdrive/auth.py
ppyan/hlstr/__init__.py
ppyan/hlstr/hlstr.py
ppyan/iter/__init__.py
ppyan/list/__init__.py
ppyan/list/flist.py
ppyan/list/str.py
ppyan/list/tocsv.py
ppyan/list/twolist.py
ppyan/login/__init__.py
ppyan/login/atadlogin.py
ppyan/mc_id/__init__.py
ppyan/nsew/__init__.py
ppyan/nsew/nsew.py
ppyann.egg-info/PKG-INFO
ppyann.egg-info/SOURCES.txt
ppyann.egg-info/dependency_links.txt
ppyann.egg-info/top_level.txt